LICENSE.txt
evo_bridge_webrtc/__init__.py
evo_bridge_webrtc/automation/api.yaml
evo_bridge_webrtc/automation/entity.yaml
evo_bridge_webrtc/control/CRtcAudioTrack.py
evo_bridge_webrtc/control/CRtcClient.py
evo_bridge_webrtc/control/CRtcServer.py
evo_bridge_webrtc/control/CRtcVideoTrack.py
evo_bridge_webrtc/control/CWebrtcApi.py
evo_bridge_webrtc/control/__init__.py
evo_bridge_webrtc/entity/ERtc.py
evo_bridge_webrtc/entity/ERtcPeer.py
evo_bridge_webrtc/entity/ERtcTask.py
evo_bridge_webrtc/entity/__init__.py
evo_bridge_webrtc/utility/UWebrtcApi.py
evo_bridge_webrtc/utility/__init__.py
evo_bridge_webrtc-2024.10.22325.dist-info/LICENSE.txt
evo_bridge_webrtc-2024.10.22325.dist-info/METADATA
evo_bridge_webrtc-2024.10.22325.dist-info/WHEEL
evo_bridge_webrtc-2024.10.22325.dist-info/RECORD
