Metadata-Version: 2.1
Name: evo-bridge-webrtc
Version: 2024.10.22325
Summary: evo-bridge-webrtc python
License: CC BY-NC-ND 4.0
Author: cyborg-ai-git
Author-email: 129898917+cyborg-ai-git@users.noreply.github.com
Requires-Python: >=3.10,<4.0
Classifier: License :: Other/Proprietary License
Classifier: Programming Language :: Python :: 3
Classifier: Programming Language :: Python :: 3.10
Classifier: Programming Language :: Python :: 3.11
Classifier: Programming Language :: Python :: 3.12
Requires-Dist: aiortc (>=1.9.0,<2.0.0)
Requires-Dist: evo-framework (>=2024.7.231312,<2025.0.0)
Requires-Dist: opencv-python (>=4.9.0.80,<5.0.0.0)
